bdtree/__init__.py
bdtree/condition.py
bdtree/exceptions.py
bdtree/node.py
bdtree/rate.py
bdtree/tree.py
bdtree/readers/__init__.py
bdtree/readers/bdtree_json_reader.py
bdtree/readers/bdtree_reader.py
bdtree-0.0.1.dist-info/LICENSE
bdtree-0.0.1.dist-info/METADATA
bdtree-0.0.1.dist-info/WHEEL
bdtree-0.0.1.dist-info/top_level.txt
bdtree-0.0.1.dist-info/RECORD
