Metadata-Version: 2.1
Name: bdtree
Version: 0.0.1
Summary: The hlpy business decision tree.
Home-page: https://github.com/hlpy-co/bdtree
Download-URL: https://github.com/hlpy-co/bdtree/archive/0.0.1.tar.gz
Author: hlpy
Author-email: hlpy-IT@hlpy.co
License: MIT
Platform: UNKNOWN
Classifier: Programming Language :: Python :: 3
Classifier: Programming Language :: Python :: 3.8
Classifier: Operating System :: OS Independent
Requires-Python: >=3.8
License-File: LICENSE
